hhj/__init__.py
hhj/hhj_engine.py
hhj_engine-1.2.dist-info/licenses/LICENSE.txt
hhj_engine-1.2.dist-info/METADATA
hhj_engine-1.2.dist-info/WHEEL
hhj_engine-1.2.dist-info/entry_points.txt
hhj_engine-1.2.dist-info/top_level.txt
hhj_engine-1.2.dist-info/RECORD
